vtag/__main__.py
vtag/core/__init__.py
vtag/core/contour.py
vtag/core/motion.py
vtag/core/tracking.py
vtag/core/utils.py
vtag/core/vtag.py
vtag/gui/colors.py
vtag/gui/dnd.py
vtag/gui/utils.py
vtag/gui/vtframe.py
vtag/gui/vtplayback.py
vtag/gui/vtplayer.py
vtagger/__main__.py
vtagger/core/__init__.py
vtagger/core/contour.py
vtagger/core/motion.py
vtagger/core/tracking.py
vtagger/core/utils.py
vtagger/core/vtag.py
vtagger/gui/colors.py
vtagger/gui/dnd.py
vtagger/gui/utils.py
vtagger/gui/vtframe.py
vtagger/gui/vtplayback.py
vtagger/gui/vtplayer.py
vtagger-0.9.0.dist-info/LICENSE
vtagger-0.9.0.dist-info/METADATA
vtagger-0.9.0.dist-info/WHEEL
vtagger-0.9.0.dist-info/top_level.txt
vtagger-0.9.0.dist-info/RECORD
